pyrfume/__init__.py
pyrfume/base.py
pyrfume/benchmarking.py
pyrfume/bushdid.py
pyrfume/cabinets.py
pyrfume/cleaning.py
pyrfume/datajoint_tools.py
pyrfume/dbtables.py
pyrfume/dravnieks.py
pyrfume/dream.py
pyrfume/embedding.py
pyrfume/experiments.py
pyrfume/features.py
pyrfume/haddad.py
pyrfume/intensity.py
pyrfume/keller.py
pyrfume/loaders/__init__.py
pyrfume/loaders/manoel_2016.py
pyrfume/mol2networx.py
pyrfume/objects.py
pyrfume/odorants.py
pyrfume/optimization.py
pyrfume/physics.py
pyrfume/plotting.py
pyrfume/predictions.py
pyrfume/pubchem.py
pyrfume/sigma_ff.py
pyrfume/snitz.py
pyrfume/unit_test/__main__.py
pyrfume/unit_test/load_manifest.ipynb
pyrfume/unit_test/test_benchmarking.py
pyrfume/unit_test/test_config_data.py
pyrfume/unit_test/test_datajoint_tools.py
pyrfume/unit_test/test_docs.py
pyrfume/unit_test/test_features.py
pyrfume/unit_test/test_load_data.py
pyrfume/unit_test/test_make_solutions.py
pyrfume/unit_test/test_mixture.py
pyrfume/unit_test/test_odorants.py
pyrfume/unit_test/test_others_in__init__.py
pyrfume/unit_test/test_physics.py
pyrfume/unit_test/test_test.py
pyrfume/unit_test/unittest_utils.py
pyrfume/westeros.py
pyrfume-0.20.dist-info/LICENSE
pyrfume-0.20.dist-info/METADATA
pyrfume-0.20.dist-info/WHEEL
pyrfume-0.20.dist-info/RECORD
