Metadata-Version: 2.3
Name: pyrfume
Version: 0.20
Summary: A validation library for human olfactory psychophysics research.
License: MIT
Author: Rick Gerkin
Author-email: rgerkin@asu.edu
Requires-Python: >=3.9,<4.0
Classifier: License :: OSI Approved :: MIT License
Classifier: Programming Language :: Python :: 3
Classifier: Programming Language :: Python :: 3.9
Classifier: Programming Language :: Python :: 3.10
Classifier: Programming Language :: Python :: 3.11
Classifier: Programming Language :: Python :: 3.12
Classifier: Programming Language :: Python :: 3.13
Provides-Extra: optimize
Requires-Dist: PubChemPy (>=1.0.4,<2.0.0)
Requires-Dist: dask[bag] (<=2021.3.0) ; extra == "optimize"
Requires-Dist: datajoint (>0.12)
Requires-Dist: deap (>=1.3.1,<2.0.0) ; extra == "optimize"
Requires-Dist: eden-kernel (>=0.3.1348,<0.4.0)
Requires-Dist: ipykernel (>=5.5.6)
Requires-Dist: lxml (<=5.1.1)
Requires-Dist: mordredcommunity (>=2.0.5,<3.0.0)
Requires-Dist: numpy (>=1.22,<2.0)
Requires-Dist: pandas (>=1.4)
Requires-Dist: plotly (>=5.9.0,<6.0.0)
Requires-Dist: quantities (>=0.13.0,<0.14.0)
Requires-Dist: rdkit (>=2023.9.3)
Requires-Dist: requests (>=2.20.0)
Requires-Dist: scikit-learn (>=0.23.1)
Requires-Dist: scipy (>=1.8)
Requires-Dist: sympy (>=1.6)
Requires-Dist: toml (>=0.10.2,<0.11.0)
Project-URL: Documentation, https://pyrfume.readthedocs.io
Project-URL: Homepage, http://pyrfume.org
